securehillhell/__init__.py
securehillhell-0.1.dist-info/METADATA
securehillhell-0.1.dist-info/WHEEL
securehillhell-0.1.dist-info/top_level.txt
securehillhell-0.1.dist-info/RECORD
