Metadata-Version: 2.1
Name: securehillhell
Version: 0.1
Summary: Cryptography examples: Hill cipher and Diffie-Hellman
Author: Durga Maduru
Author-email: your.email@example.com
Classifier: Programming Language :: Python :: 3
Classifier: License :: OSI Approved :: MIT License
Classifier: Operating System :: OS Independent
Requires-Python: >=3.6
